sldp_grabber/__init__.py
sldp_grabber/cli.py
sldp_grabber/grabber.py
sldp_grabber/utils.py
sldp_grabber-1.0.0.dist-info/METADATA
sldp_grabber-1.0.0.dist-info/WHEEL
sldp_grabber-1.0.0.dist-info/entry_points.txt
sldp_grabber-1.0.0.dist-info/top_level.txt
sldp_grabber-1.0.0.dist-info/RECORD
