Metadata-Version: 2.4
Name: sldp-grabber
Version: 1.0.0
Summary: A tool to grab streams from SLDP WebSocket servers and save/mux them
Home-page: https://github.com/dgkn94/sldp-grabber
Author: SLDP Grabber
Author-email: dgkn94 <ddev940x@outlook.com>
License: MIT
Project-URL: Homepage, https://github.com/dgkn94/sldp-grabber
Project-URL: Repository, https://github.com/dgkn94/sldp-grabber
Project-URL: Issues, https://github.com/dgkn94/sldp-grabber/issues
Project-URL: Changelog, https://github.com/dgkn94/sldp-grabber/releases
Keywords: sldp,websocket,streaming,h264,aac,opus
Classifier: Development Status :: 4 - Beta
Classifier: Intended Audience :: Developers
Classifier: License :: OSI Approved :: MIT License
Classifier: Operating System :: OS Independent
Classifier: Programming Language :: Python :: 3
Classifier: Programming Language :: Python :: 3.7
Classifier: Programming Language :: Python :: 3.8
Classifier: Programming Language :: Python :: 3.9
Classifier: Programming Language :: Python :: 3.10
Classifier: Programming Language :: Python :: 3.11
Classifier: Topic :: Multimedia :: Video
Classifier: Topic :: Utilities
Requires-Python: >=3.7
Requires-Dist: websocket-client>=1.3.0
Dynamic: author
Dynamic: home-page
Dynamic: requires-python
